config/__init__.py
config/settings.py
src/__init__.py
src/install_cron.py
src/main.py
src/modules/__init__.py
src/modules/supabasefuncs.py
src/modules/utilities.py
src/scripts/__init__.py
src/scripts/get_power_info.py
src/scripts/simplev7.py
power_corn-0.5.dist-info/LICENSE
power_corn-0.5.dist-info/METADATA
power_corn-0.5.dist-info/WHEEL
power_corn-0.5.dist-info/entry_points.txt
power_corn-0.5.dist-info/top_level.txt
power_corn-0.5.dist-info/RECORD
