Metadata-Version: 2.1
Name: power_corn
Version: 0.5
License-File: LICENSE
Requires-Dist: supabase
